device42api
