Metadata-Version: 1.0
Name: device42api
Version: 1.2.1
Summary: Device42.com API module for object oriented API handling
Home-page: http://python-device42api.readthedocs.org/en/latest/
Author: Michael Lang
Author-email: Michael.Lang@ctbto.org
License: GPLv2
Platform: UNKNOWN
Classifier: Development Status :: 5 - Production/Stable
Classifier: Environment :: Console
Classifier: Intended Audience :: Developers
Classifier: Intended Audience :: Education
Classifier: License :: OSI Approved :: GNU General Public License v2 (GPLv2)
Classifier: Operating System :: OS Independent
Classifier: Programming Language :: Python
Classifier: Programming Language :: Python :: 2
Classifier: Topic :: Documentation
Classifier: Topic :: Text Processing
Classifier: Topic :: Utilities
